alist/__init__.py
alist/account.py
alist/admin.py
alist/driver.py
alist/meta.py
alist/public.py
alist/setting.py
alist/utils.py
python_alist_api-0.0.4.dist-info/LICENSE
python_alist_api-0.0.4.dist-info/METADATA
python_alist_api-0.0.4.dist-info/WHEEL
python_alist_api-0.0.4.dist-info/top_level.txt
python_alist_api-0.0.4.dist-info/RECORD
