Metadata-Version: 2.1
Name: python-alist-api
Version: 0.0.4
Summary: Python wrapper for the Alist API
Author-email: Kai Peng <pkemb@outlook.com>
Maintainer-email: Kai Peng <pkemb@outlook.com>
License: The MIT License (MIT)
Project-URL: Homepage, https://github.com/pkemb/python-alist-api
Project-URL: Bug Reports, https://github.com/pkemb/python-alist-api/issues
Project-URL: Funding, https://github.com/pkemb/python-alist-api
Project-URL: Say Thanks!, https://github.com/pkemb/python-alist-api
Project-URL: Source, https://github.com/pkemb/python-alist-api/
Keywords: Alist,API,Python
Classifier: Development Status :: 3 - Alpha
Classifier: Environment :: Console
Classifier: Intended Audience :: Developers
Classifier: Topic :: Software Development :: User Interfaces
Classifier: License :: OSI Approved :: MIT License
Classifier: Programming Language :: Python :: 3
Requires-Python: >=3.0
License-File: LICENSE
Requires-Dist: requests
